odoo/addons/stock_buffer_capacity_limit/README.rst
odoo/addons/stock_buffer_capacity_limit/__init__.py
odoo/addons/stock_buffer_capacity_limit/__manifest__.py
odoo/addons/stock_buffer_capacity_limit/i18n/it.po
odoo/addons/stock_buffer_capacity_limit/i18n/stock_buffer_capacity_limit.pot
odoo/addons/stock_buffer_capacity_limit/models/__init__.py
odoo/addons/stock_buffer_capacity_limit/models/stock_buffer.py
odoo/addons/stock_buffer_capacity_limit/readme/CONTRIBUTORS.rst
odoo/addons/stock_buffer_capacity_limit/readme/DESCRIPTION.rst
odoo/addons/stock_buffer_capacity_limit/readme/HISTORY.rst
odoo/addons/stock_buffer_capacity_limit/static/description/icon.png
odoo/addons/stock_buffer_capacity_limit/static/description/index.html
odoo/addons/stock_buffer_capacity_limit/tests/__init__.py
odoo/addons/stock_buffer_capacity_limit/tests/test_stock_buffer_capacity_limit.py
odoo/addons/stock_buffer_capacity_limit/views/stock_buffer_view.xml
odoo13_addon_stock_buffer_capacity_limit-13.0.1.2.0.dist-info/METADATA
odoo13_addon_stock_buffer_capacity_limit-13.0.1.2.0.dist-info/WHEEL
odoo13_addon_stock_buffer_capacity_limit-13.0.1.2.0.dist-info/top_level.txt
odoo13_addon_stock_buffer_capacity_limit-13.0.1.2.0.dist-info/RECORD
